lock/lock.vhdl
LIBRARY IEEE;
USE IEEE.STD_LOGIC_1164.ALL;

entity lock is
  port(input:in std_logic_vector(3 downto 0);
       mode: in std_logic_vector(1 downto 0);
       clk: in std_logic;
       rst: in std_logic;
       succ: out std_logic;
       fail: out std_logic;
       locked: out std_logic
     );
end lock;

architecture bhv of lock is
  type state_type is (IDLE, ADMIN_0, ADMIN_1, ADMIN_2, ADMIN_3, VERIFY_0, VERIFY_1, VERIFY_2, VERIFY_3, SET_0, SET_1, SET_2, SET_3, SUCCESS);
  type lock_type is (INITIAL, TRY_1, TRY_2, TRY_3);
  signal state: state_type := IDLE;
  signal lock: lock_type := INITIAL;
  signal pass0: std_logic_vector(3 downto 0) := "0001";
  signal pass1: std_logic_vector(3 downto 0) := "0010";
  signal pass2: std_logic_vector(3 downto 0) := "0100";
  signal pass3: std_logic_vector(3 downto 0) := "1000";

  signal admin0: std_logic_vector(3 downto 0) := "0001";
  signal admin1: std_logic_vector(3 downto 0) := "0010";
  signal admin2: std_logic_vector(3 downto 0) := "0100";
  signal admin3: std_logic_vector(3 downto 0) := "1000";
begin
  process(state)
  begin
    case state is
      when IDLE =>
        fail <= '1';
        succ <= '0';

      when SUCCESS =>
        fail <= '0';
        succ <= '1';

      when others =>
        fail <= '0';
        succ <= '0';
    end case;
  end process;

  process(lock, state)
  begin
    if(lock = TRY_3 and state /= VERIFY_0 and state /= VERIFY_1 and state /= VERIFY_2 and state /= VERIFY_3) then
      locked <= '1';
    else
      locked <= '0';
    end if;
  end process;

  process(rst, clk)
  begin
    if(rst = '1') then
      if mode = "01" then
        if lock /= TRY_3 then
          state <= VERIFY_0;

          case lock is
            when INITIAL =>
              lock <= TRY_1;
            when TRY_1 =>
              lock <= TRY_2;
            when others =>
              lock <= TRY_3;
          end case;
        end if;
      elsif mode = "00" then
        if state = SUCCESS then
          state <= SET_0;
        end if;
      elsif mode = "10" then
        state <= ADMIN_0;
      end if;
    elsif rising_edge(clk) then
      case state is
        when ADMIN_0 =>
          if admin0 /= input then
            state <= IDLE;
          else
            state <= ADMIN_1;
          end if;

        when ADMIN_1 =>
          if admin1 /= input then
            state <= IDLE;
          else
            state <= ADMIN_2;
          end if;

        when ADMIN_2 =>
          if admin2 /= input then
            state <= IDLE;
          else
            state <= ADMIN_3;
          end if;

        when ADMIN_3 =>
          if admin3 /= input then
            state <= IDLE;
          else
            state <= SUCCESS;
            lock <= INITIAL;
          end if;

        when VERIFY_0 =>
          if pass0 /= input then
            state <= IDLE;
          else
            state <= VERIFY_1;
          end if;

        when VERIFY_1 =>
          if pass1 /= input then
            state <= IDLE;
          else
            state <= VERIFY_2;
          end if;

        when VERIFY_2 =>
          if pass2 /= input then
            state <= IDLE;
          else
            state <= VERIFY_3;
          end if;

        when VERIFY_3 =>
          if pass3 /= input then
            state <= IDLE;
          else
            state <= SUCCESS;
            lock <= INITIAL;
          end if;

        when SET_0 =>
          pass0 <= input;
          state <= SET_1;

        when SET_1 =>
          pass1 <= input;
          state <= SET_2;

        when SET_2 =>
          pass2 <= input;
          state <= SET_3;

        when SET_3 =>
          pass3 <= input;
          state <= SUCCESS;

        when others =>
          state <= state;
      end case;
    end if;
  end process;
end bhv;

lock/tb.vhdl
LIBRARY IEEE;
USE IEEE.STD_LOGIC_1164.ALL;

entity tb is
end tb;

architecture bhv of tb is
  component lock is
    port(input:in std_logic_vector(3 downto 0);
         mode: in std_logic_vector(1 downto 0);
         clk: in std_logic;
         rst: in std_logic;
         succ: out std_logic;
         fail: out std_logic
       );
  end component;

  signal i: std_logic_vector(3 downto 0) := "0000";
  signal m: std_logic_vector(1 downto 0) := "00";
  signal c: std_logic := '0';
  signal r: std_logic := '0';
  signal s: std_logic;
  signal f: std_logic;
begin
  l: lock port map(input => i, mode => m, clk => c, rst => r, succ => s, fail => f);

  process
  begin
    loop
      -- Verify default
      m <= "01";
      wait for 1 us;
      r <= '1';
      wait for 1 us;
      r <= '0';

      i <= "0001";
      wait for 1 us;
      c <= '1';
      wait for 1 us;
      c <= '0';

      i <= "0010";
      wait for 1 us;
      c <= '1';
      wait for 1 us;
      c <= '0';

      i <= "0100";
      wait for 1 us;
      c <= '1';
      wait for 1 us;
      c <= '0';

      i <= "1000";
      wait for 1 us;
      c <= '1';
      wait for 1 us;
      c <= '0';

      wait for 10 us;

      -- Set
      m <= "00";
      wait for 1 us;
      r <= '1';
      wait for 1 us;
      r <= '0';

      i <= "1000";
      wait for 1 us;
      c <= '1';
      wait for 1 us;
      c <= '0';

      i <= "0100";
      wait for 1 us;
      c <= '1';
      wait for 1 us;
      c <= '0';

      i <= "0010";
      wait for 1 us;
      c <= '1';
      wait for 1 us;
      c <= '0';

      i <= "0001";
      wait for 1 us;
      c <= '1';
      wait for 1 us;
      c <= '0';

      wait for 10 us;

      -- Verify default
      m <= "01";
      wait for 1 us;
      r <= '1';
      wait for 1 us;
      r <= '0';

      i <= "0001";
      wait for 1 us;
      c <= '1';
      wait for 1 us;
      c <= '0';

      i <= "0010";
      wait for 1 us;
      c <= '1';
      wait for 1 us;
      c <= '0';

      i <= "0100";
      wait for 1 us;
      c <= '1';
      wait for 1 us;
      c <= '0';

      i <= "1000";
      wait for 1 us;
      c <= '1';
      wait for 1 us;
      c <= '0';

      wait for 10 us;

      -- Verify default
      m <= "01";
      wait for 1 us;
      r <= '1';
      wait for 1 us;
      r <= '0';

      i <= "0001";
      wait for 1 us;
      c <= '1';
      wait for 1 us;
      c <= '0';

      i <= "0010";
      wait for 1 us;
      c <= '1';
      wait for 1 us;
      c <= '0';

      i <= "0100";
      wait for 1 us;
      c <= '1';
      wait for 1 us;
      c <= '0';

      i <= "1000";
      wait for 1 us;
      c <= '1';
      wait for 1 us;
      c <= '0';

      wait for 10 us;

      -- Verify partial
      m <= "01";
      wait for 1 us;
      r <= '1';
      wait for 1 us;
      r <= '0';

      i <= "1000";
      wait for 1 us;
      c <= '1';
      wait for 1 us;
      c <= '0';

      i <= "0100";
      wait for 1 us;
      c <= '1';
      wait for 1 us;
      c <= '0';

      i <= "0010";
      wait for 1 us;
      c <= '1';
      wait for 1 us;
      c <= '0';

      i <= "1111";
      wait for 1 us;
      c <= '1';
      wait for 1 us;
      c <= '0';

      wait for 10 us;

      -- Now is locked

      -- Correct pass
      m <= "01";
      wait for 1 us;
      r <= '1';
      wait for 1 us;
      r <= '0';

      i <= "1000";
      wait for 1 us;
      c <= '1';
      wait for 1 us;
      c <= '0';

      i <= "0100";
      wait for 1 us;
      c <= '1';
      wait for 1 us;
      c <= '0';

      i <= "0010";
      wait for 1 us;
      c <= '1';
      wait for 1 us;
      c <= '0';

      i <= "0001";
      wait for 1 us;
      c <= '1';
      wait for 1 us;
      c <= '0';

      wait for 10 us;

      -- Still locked

      -- Incorrect Admin
      m <= "10";
      wait for 1 us;
      r <= '1';
      wait for 1 us;
      r <= '0';

      i <= "0001";
      wait for 1 us;
      c <= '1';
      wait for 1 us;
      c <= '0';

      i <= "0010";
      wait for 1 us;
      c <= '1';
      wait for 1 us;
      c <= '0';

      i <= "0100";
      wait for 1 us;
      c <= '1';
      wait for 1 us;
      c <= '0';

      i <= "1001";
      wait for 1 us;
      c <= '1';
      wait for 1 us;
      c <= '0';

      wait for 10 us;

      -- Admin
      m <= "10";
      wait for 1 us;
      r <= '1';
      wait for 1 us;
      r <= '0';

      i <= "0001";
      wait for 1 us;
      c <= '1';
      wait for 1 us;
      c <= '0';

      i <= "0010";
      wait for 1 us;
      c <= '1';
      wait for 1 us;
      c <= '0';

      i <= "0100";
      wait for 1 us;
      c <= '1';
      wait for 1 us;
      c <= '0';

      i <= "1000";
      wait for 1 us;
      c <= '1';
      wait for 1 us;
      c <= '0';

      wait for 10 us;

      -- Correct pass
      m <= "01";
      wait for 1 us;
      r <= '1';
      wait for 1 us;
      r <= '0';

      i <= "1000";
      wait for 1 us;
      c <= '1';
      wait for 1 us;
      c <= '0';

      i <= "0100";
      wait for 1 us;
      c <= '1';
      wait for 1 us;
      c <= '0';

      i <= "0010";
      wait for 1 us;
      c <= '1';
      wait for 1 us;
      c <= '0';

      i <= "0001";
      wait for 1 us;
      c <= '1';
      wait for 1 us;
      c <= '0';

      wait for 10 us;

      std.env.stop(0);
    end loop;
  end process;
end bhv;

lock/wave.vcd
$date
  Fri May 24 21:30:01 2019
$end
$version
  GHDL v0
$end
$timescale
  1 fs
$end
$scope module standard $end
$upscope $end
$scope module textio $end
$upscope $end
$scope module std_logic_1164 $end
$upscope $end
$scope module env $end
$upscope $end
$scope module tb $end
$var reg 4 ! i[3:0] $end
$var reg 2 " m[1:0] $end
$var reg 1 # c $end
$var reg 1 $ r $end
$var reg 1 % s $end
$var reg 1 & f $end
$scope module l $end
$var reg 4 ' input[3:0] $end
$var reg 2 ( mode[1:0] $end
$var reg 1 ) clk $end
$var reg 1 * rst $end
$var reg 1 + succ $end
$var reg 1 , fail $end
$var reg 1 - locked $end
$comment state is not handled $end
$comment lock is not handled $end
$var reg 4 . pass0[3:0] $end
$var reg 4 / pass1[3:0] $end
$var reg 4 0 pass2[3:0] $end
$var reg 4 1 pass3[3:0] $end
$var reg 4 2 admin0[3:0] $end
$var reg 4 3 admin1[3:0] $end
$var reg 4 4 admin2[3:0] $end
$var reg 4 5 admin3[3:0] $end
$upscope $end
$upscope $end
$enddefinitions $end
#0
b0000 !
b01 "
0#
0$
0%
1&
b0000 '
b01 (
0)
0*
0+
1,
0-
b0001 .
b0010 /
b0100 0
b1000 1
b0001 2
b0010 3
b0100 4
b1000 5
#1000000000
1$
0&
1*
0,
#2000000000
b0001 !
0$
b0001 '
0*
#3000000000
1#
1)
#4000000000
b0010 !
0#
b0010 '
0)
#5000000000
1#
1)
#6000000000
b0100 !
0#
b0100 '
0)
#7000000000
1#
1)
#8000000000
b1000 !
0#
b1000 '
0)
#9000000000
1#
1%
1)
1+
#10000000000
0#
0)
#20000000000
b00 "
b00 (
#21000000000
1$
0%
1*
0+
#22000000000
0$
0*
#23000000000
1#
1)
b1000 .
#24000000000
b0100 !
0#
b0100 '
0)
#25000000000
1#
1)
b0100 /
#26000000000
b0010 !
0#
b0010 '
0)
#27000000000
1#
1)
b0010 0
#28000000000
b0001 !
0#
b0001 '
0)
#29000000000
1#
1%
1)
1+
b0001 1
#30000000000
0#
0)
#40000000000
b01 "
b01 (
#41000000000
1$
0%
1*
0+
#42000000000
0$
0*
#43000000000
1#
1&
1)
1,
#44000000000
b0010 !
0#
b0010 '
0)
#45000000000
1#
1)
#46000000000
b0100 !
0#
b0100 '
0)
#47000000000
1#
1)
#48000000000
b1000 !
0#
b1000 '
0)
#49000000000
1#
1)
#50000000000
0#
0)
#60000000000
#61000000000
1$
0&
1*
0,
#62000000000
b0001 !
0$
b0001 '
0*
#63000000000
1#
1&
1)
1,
#64000000000
b0010 !
0#
b0010 '
0)
#65000000000
1#
1)
#66000000000
b0100 !
0#
b0100 '
0)
#67000000000
1#
1)
#68000000000
b1000 !
0#
b1000 '
0)
#69000000000
1#
1)
#70000000000
0#
0)
#80000000000
#81000000000
1$
0&
1*
0,
#82000000000
0$
0*
#83000000000
1#
1)
#84000000000
b0100 !
0#
b0100 '
0)
#85000000000
1#
1)
#86000000000
b0010 !
0#
b0010 '
0)
#87000000000
1#
1)
#88000000000
b1111 !
0#
b1111 '
0)
#89000000000
1#
1&
1)
1,
1-
#90000000000
0#
0)
#100000000000
#101000000000
1$
1*
#102000000000
b1000 !
0$
b1000 '
0*
#103000000000
1#
1)
#104000000000
b0100 !
0#
b0100 '
0)
#105000000000
1#
1)
#106000000000
b0010 !
0#
b0010 '
0)
#107000000000
1#
1)
#108000000000
b0001 !
0#
b0001 '
0)
#109000000000
1#
1)
#110000000000
0#
0)
#120000000000
b10 "
b10 (
#121000000000
1$
0&
1*
0,
#122000000000
0$
0*
#123000000000
1#
1)
#124000000000
b0010 !
0#
b0010 '
0)
#125000000000
1#
1)
#126000000000
b0100 !
0#
b0100 '
0)
#127000000000
1#
1)
#128000000000
b1001 !
0#
b1001 '
0)
#129000000000
1#
1&
1)
1,
#130000000000
0#
0)
#140000000000
#141000000000
1$
0&
1*
0,
#142000000000
b0001 !
0$
b0001 '
0*
#143000000000
1#
1)
#144000000000
b0010 !
0#
b0010 '
0)
#145000000000
1#
1)
#146000000000
b0100 !
0#
b0100 '
0)
#147000000000
1#
1)
#148000000000
b1000 !
0#
b1000 '
0)
#149000000000
1#
1%
1)
1+
0-
#150000000000
0#
0)
#160000000000
b01 "
b01 (
#161000000000
1$
0%
1*
0+
#162000000000
0$
0*
#163000000000
1#
1)
#164000000000
b0100 !
0#
b0100 '
0)
#165000000000
1#
1)
#166000000000
b0010 !
0#
b0010 '
0)
#167000000000
1#
1)
#168000000000
b0001 !
0#
b0001 '
0)
#169000000000
1#
1%
1)
1+
#170000000000
0#
0)
